freeze_core/__init__.py
freeze_core/_compat.py
freeze_core/util.c
freeze_core/util.pyi
freeze_core/winmsvcr.py
freeze_core/winmsvcr_repack.py
freeze_core/__pycache__/__init__.cpython-311.opt-1.pyc
freeze_core/__pycache__/_compat.cpython-311.opt-1.pyc
freeze_core/__pycache__/winmsvcr.cpython-311.opt-1.pyc
freeze_core/__pycache__/winmsvcr_repack.cpython-311.opt-1.pyc
freeze_core/bases/Win32GUI.c
freeze_core/bases/Win32Service.c
freeze_core/bases/__init__.py
freeze_core/bases/_common.c
freeze_core/bases/console-cpython-311-x86_64-linux-musl
freeze_core/bases/console.c
freeze_core/bases/dummy.rc
freeze_core/bases/manifest.rc
freeze_core/bases/python.manifest
freeze_core/bases/__pycache__/__init__.cpython-311.opt-1.pyc
freeze_core/icons/__init__.py
freeze_core/icons/launcher.icns
freeze_core/icons/launcher.ico
freeze_core/icons/launcher.svg
freeze_core/icons/logo.svg
freeze_core/icons/logox128.png
freeze_core/icons/py.icns
freeze_core/icons/py.ico
freeze_core/icons/py.png
freeze_core/icons/py.svg
freeze_core/icons/pyc.icns
freeze_core/icons/pyc.ico
freeze_core/icons/pyc.svg
freeze_core/icons/pyd.icns
freeze_core/icons/pyd.ico
freeze_core/icons/pyd.svg
freeze_core/icons/python.icns
freeze_core/icons/python.ico
freeze_core/icons/python.svg
freeze_core/icons/pythonw.icns
freeze_core/icons/pythonw.ico
freeze_core/icons/pythonw.svg
freeze_core/icons/pythonwx150.png
freeze_core/icons/pythonwx44.png
freeze_core/icons/pythonx150.png
freeze_core/icons/pythonx44.png
freeze_core/icons/pythonx50.png
freeze_core/icons/setup.icns
freeze_core/icons/setup.ico
freeze_core/icons/setup.svg
freeze_core/icons/__pycache__/__init__.cpython-311.opt-1.pyc
freeze_core/include/pythoncapi_compat.h
freeze_core/initscripts/__init__.py
freeze_core/initscripts/__startup__.py
freeze_core/initscripts/console.py
freeze_core/initscripts/consolesetlibpath.py
freeze_core/initscripts/sharedlib.py
freeze_core/initscripts/sharedlibsource.py
freeze_core-0.4.2.dist-info/METADATA
freeze_core-0.4.2.dist-info/WHEEL
freeze_core-0.4.2.dist-info/top_level.txt
freeze_core-0.4.2.dist-info/RECORD
freeze_core-0.4.2.dist-info/licenses/LICENSE
freeze_core-0.4.2.dist-info/sboms/auditwheel.cdx.json
