Metadata-Version: 2.4
Name: freeze-core
Version: 0.4.2
Summary: Core dependency for cx_Freeze
Author-email: Marcelo Duarte <marcelotduarte@users.noreply.github.com>
License-Expression: MIT
Project-URL: Home, https://marcelotduarte.github.io/cx_Freeze
Project-URL: Changelog, https://github.com/marcelotduarte/freeze-core/releases
Project-URL: Documentation, https://cx-freeze.readthedocs.io
Project-URL: Source, https://github.com/marcelotduarte/freeze-core
Project-URL: Tracker, https://github.com/marcelotduarte/cx_Freeze/issues
Keywords: freeze-core freeze cx-freeze cxfreeze cx_Freeze python
Classifier: Development Status :: 5 - Production/Stable
Classifier: Intended Audience :: Developers
Classifier: Natural Language :: English
Classifier: Operating System :: OS Independent
Classifier: Programming Language :: C
Classifier: Programming Language :: Python
Classifier: Programming Language :: Python :: 3
Classifier: Programming Language :: Python :: 3 :: Only
Classifier: Programming Language :: Python :: 3.9
Classifier: Programming Language :: Python :: 3.10
Classifier: Programming Language :: Python :: 3.11
Classifier: Programming Language :: Python :: 3.12
Classifier: Programming Language :: Python :: 3.13
Classifier: Programming Language :: Python :: 3.14
Classifier: Programming Language :: Python :: Free Threading :: 2 - Beta
Classifier: Topic :: Software Development :: Build Tools
Classifier: Topic :: Software Development :: Libraries :: Python Modules
Classifier: Topic :: System :: Software Distribution
Classifier: Topic :: Utilities
Requires-Python: >=3.10
License-File: LICENSE
Requires-Dist: filelock>=3.15.3
Requires-Dist: cabarchive>=0.2.4; sys_platform == "win32"
Requires-Dist: striprtf>=0.0.26; sys_platform == "win32"
Provides-Extra: dev
Requires-Dist: bump-my-version==1.2.4; extra == "dev"
Requires-Dist: cibuildwheel==3.3.0; extra == "dev"
Requires-Dist: pre-commit==4.5.0; extra == "dev"
Provides-Extra: tests
Requires-Dist: coverage==7.12.0; extra == "tests"
Requires-Dist: pytest==9.0.1; extra == "tests"
Dynamic: license-file
